{
    "app.init": "Démarrage de l'application (APP_ROOT: {root})",
    "app.init_success": "Application initialisée avec succès.",
    "app.init_fail": "Échec critique lors de la construction de l'application.",
    
    "map_importer.init": "MapImporter (Service) initialisé.",
    "map_importer.worker.init": "MapImportWorker: Démarrage de l'importation de '{path}'...",
    "map_importer.worker.no_data": "MapImportWorker: Le fichier '{path}' ne contenait aucun nœud ou arête.",
    "map_importer.worker.success": "MapImportWorker: Importation terminée. {nodes} nœuds, {edges} arêtes.",
    "map_importer.worker.xml_error": "MapImportWorker: Erreur de syntaxe XML lors de la lecture de '{path}': {e}",
    "map_importer.worker.error": "MapImportWorker: Erreur inattendue lors de l'importation de la carte: {e}",
    "map_importer.load_map.no_path": "MapImporter: 'load_map' appelé avec un chemin vide.",

    "data_importer.init": "DataImporter (Service) initialisé.",
    "data_importer.worker.init": "DataImportWorker: Analyse de '{path}'...",
    "data_importer.worker.no_data": "DataImportWorker: Aucune source de données valide trouvée dans {path}",
    "data_importer.worker.unknown_type": "DataImportWorker: Type d'association inconnu '{type}'. Utilisation de UNASSOCIATED.",
    "data_importer.worker.success": "DataImportWorker: Analyse terminée pour {path}. Types: {types}",
    "data_importer.worker.error": "DataImportWorker: Échec de l'analyse de {path}: {e}",
    "data_importer.add_source.no_path": "DataImporter: Chemin de dossier invalide fourni: '{path}'",

    "persistence.init": "PersistenceService (Service) initialisé.",
    "persistence.worker.init": "PersistenceWorker: Démarrage de l'enregistrement dans '{path}'...",
    "persistence.worker.success": "PersistenceWorker: Configuration enregistrée avec succès dans {path}",
    "persistence.worker.sqlite_error": "PersistenceWorker: Erreur SQLite lors de l'enregistrement dans {path}: {e}",
    "persistence.worker.error": "PersistenceWorker: Échec inattendu lors de l'enregistrement de la configuration: {e}",
    "persistence.save.no_path": "PersistenceService: 'save_configuration' appelé avec un chemin vide.",
    "persistence.save.fix_path": "PersistenceService: Nom de fichier corrigé en '{path}'",

    "project.init": "ProjectService (Service) initialisé.",
    "project.save.worker.init": "ProjectSaveWorker: Démarrage de l'enregistrement dans '{path}'...",
    "project.save.worker.success": "ProjectSaveWorker: Projet enregistré avec succès dans {path}",
    "project.save.worker.error": "ProjectSaveWorker: Échec inattendu lors de l'enregistrement du projet: {e}",
    "project.load.worker.init": "ProjectLoadWorker: Démarrage du chargement de '{path}'...",
    "project.load.worker.success": "ProjectLoadWorker: Projet '{path}' chargé avec succès.",
    "project.load.worker.error": "ProjectLoadWorker: Échec inattendu lors du chargement du projet: {e}",
    "project.save.no_path": "ProjectService: 'save_project' appelé avec un chemin vide.",
    "project.load.no_path": "ProjectService: 'load_project' appelé avec un chemin vide.",

    "config.init": "ConfigManager: Initialisé pour le chemin: {path}",
    "config.load.success": "ConfigManager: Configuration chargée depuis {path}",
    "config.load.not_found": "Avertissement: Fichier de configuration non trouvé à {path}. Utilisation des valeurs par défaut.",
    "config.load.parse_error": "CRITIQUE: Échec de l'analyse de {path}: {e}. Utilisation des valeurs par défaut.",
    "config.load.read_error": "CRITIQUE: Échec de la lecture de {path}: {e}. Utilisation des valeurs par défaut.",
    "config.save.success": "ConfigManager: Configuration enregistrée dans {path}",
    "config.save.error": "CRITIQUE: Échec de l'écriture de la configuration dans {path}: {e}",

    "i18n.load.success": "Traductions chargées depuis: {path}",
    "i18n.load.not_found": "Erreur: Fichier de traduction non trouvé: {path}",
    "i18n.load.parse_error": "Erreur: Erreur lors du décodage du JSON: {path}",
    "i18n.t.not_found": "Avertissement: Clé de traduction non trouvée: '{key}'",
    "i18n.t.format_error": "Erreur: Erreur lors du formatage de la clé '{key}': {e}",

    "controller.main.init": "MainController (Contrôleur) initialisé.",
    "controller.map.init": "MapController (Contrôleur) initialisé.",
    "controller.sources.init": "SourcesController (Contrôleur) initialisé.",
    "controller.info.init": "InfoController (Contrôleur) initialisé.",
    "controller.settings.init": "SettingsController (Contrôleur) initialisé.",

    "appstate.map.set": "AppState: Données de carte mises à jour. {nodes} nœuds, {edges} arêtes.",
    "appstate.element.update_name": "AppState: 'real_name' mis à jour pour '{id}'",
    "appstate.element.update_name_fail": "AppState: Tentative de mise à jour du nom d'un élément inconnu: '{id}'",
    "appstate.source.add_fail": "AppState: La source de données '{path}' existe déjà.",
    "appstate.source.set_type": "AppState: Association de '{name}' définie à '{type}'.",
    "appstate.source.set_type_fail": "AppState: Tentative de définition d'un type invalide: {type}",
    "appstate.assoc.enter_fail": "AppState: Tentative d'entrer en mode association sans source sélectionnée.",
    "appstate.assoc.enter_fail_used": "AppState: La source '{name}' est déjà associée. Annulez d'abord l'association.",
    "appstate.assoc.enter": "AppState: Mode d'association ACTIVÉ.",
    "appstate.assoc.exit": "AppState: Mode d'association DÉSACTIVÉ.",
    "appstate.assoc.associate_fail": "AppState: Tentative d'association, mais aucune source n'était sélectionnée.",
    "appstate.assoc.associate_busy": "AppState: La source '{name}' était déjà associée. Ignoré.",
    "appstate.assoc.associated": "AppState: Source '{name}' associée à l'élément '{id}'.",
    "appstate.source.delete_fail": "AppState: Tentative de suppression d'une source inconnue: {id}",
    "appstate.source.deleted": "AppState: Source de données '{name}' supprimée.",
    "appstate.source.toggled": "AppState: Association de '{name}' changée en '{type}'.",
    "appstate.editor.unassign": "AppState: Source '{name}' libérée de '{id}'.",
    "appstate.editor.move": "AppState: Source '{name}' déplacée de '{old_id}' vers '{new_id}'.",
    "appstate.editor.assign": "AppState: Source '{name}' associée à '{id}' (via l'Éditeur).",
    "appstate.savable.map_missing": "AppState: Non enregistrable (carte non chargée).",
    "appstate.savable.source_unassigned": "AppState: Non enregistrable (Source locale '{name}' non associée).",
    "appstate.savable.ok": "AppState: État enregistrable.",

    "view.main.init": "MainWindow (View) initialisée.",
    "view.map.init": "MapView (View) initialisée.",
    "view.sources.init": "SourcesPanel (View) initialisé.",
    "view.editor.init": "EditorPanel (View) initialisé.",
    "view.settings.init": "SettingsDialog (View) initialisé.",

    "renderer.map.init": "MapRenderer (Pintor) initialisé.",
    "renderer.map.draw.init": "MapRenderer: Lecture des données de la carte depuis AppState...",
    "renderer.map.draw.no_data": "MapRenderer: Aucune donnée de carte à dessiner.",
    "renderer.map.draw.success": "MapRenderer: Carte dessinée. {nodes} nœuds, {edges} (sur {total_edges}) arêtes rendues.",
    "renderer.map.draw.fit_fail": "MapView: Erreur lors de la tentative d'ajustement du zoom: {e}",
    "renderer.map.draw.fit_ok": "MapView: Zoom ajusté à la carte. (Rect: {rect})",
    "renderer.map.zoom_limits": "MapView: Limites de zoom définies (Min: {min}, Max: {max})",
    "renderer.highlight.fail": "MapRenderer: Impossible de trouver l'élément '{id}' à mettre en surbrillance.",
    "renderer.highlight.fail_hidden": "MapRenderer: Impossible de trouver l'élément '{id}' à mettre en surbrillance (peut être une arête de 'retour' non dessinée)."
}